xlog/__init__.py
xlog/xlog.py
xlog-0.0.3.dist-info/METADATA
xlog-0.0.3.dist-info/WHEEL
xlog-0.0.3.dist-info/top_level.txt
xlog-0.0.3.dist-info/RECORD
