Metadata-Version: 2.1
Name: xlog
Version: 0.0.3
Summary: Xbiome pipeline log frame
Home-page: https://github.com/xbiome-it/xlog
Author: xbiome-it
Author-email: wangxi@xbiome.com
License: UNKNOWN
Keywords: logger,logging,logger,log,Xbiome
Platform: UNKNOWN
Classifier: Development Status :: 5 - Production/Stable
Classifier: Topic :: System :: Logging
Classifier: Intended Audience :: Developers
Classifier: Natural Language :: English
Classifier: License :: OSI Approved :: MIT License
Classifier: Operating System :: OS Independent
Classifier: Programming Language :: Python :: 3
Requires-Python: >=3.5
Requires-Dist: loguru (>=0.5.3)
